sync_fifo.sv
// =============================================================================
// sync_fifo.sv
// Parameterized synchronous FIFO (single clock domain).
//
// - DATA_WIDTH : width of each entry
// - DEPTH      : number of entries, must be a power of 2 (uses the classic
//                "extra MSB pointer bit" scheme for full/empty detection)
// =============================================================================
`timescale 1ns/1ps

module sync_fifo #(
    parameter int DATA_WIDTH = 8,
    parameter int DEPTH      = 8
) (
    input  logic                  clk,
    input  logic                  rst_n,     // async active-low reset

    input  logic                  wr_en,
    input  logic [DATA_WIDTH-1:0] wdata,

    input  logic                  rd_en,
    output logic [DATA_WIDTH-1:0] rdata,

    output logic                  full,
    output logic                  empty
);

    localparam int ADDR_W = $clog2(DEPTH);

    // Storage
    logic [DATA_WIDTH-1:0] mem [0:DEPTH-1];

    // Pointers are ADDR_W+1 bits wide: the extra top bit is not a real
    // memory address, it's a "wrap parity" bit. Comparing it lets us tell
    // full apart from empty even though both conditions have wptr==rptr
    // in their lower ADDR_W bits.
    logic [ADDR_W:0] wptr, rptr;

    // Effective enables: a write while full is normally illegal and must
    // be safely dropped -- UNLESS a read is happening in the very same
    // cycle, which frees a slot at the same instant. Symmetric logic for
    // reads while empty.
    logic wr_en_eff, rd_en_eff;
    assign wr_en_eff = wr_en && (!full || rd_en);
    assign rd_en_eff = rd_en && !empty;

    // Write port
    always_ff @(posedge clk or negedge rst_n) begin
        if (!rst_n) begin
            wptr <= '0;
        end else if (wr_en_eff) begin
            mem[wptr[ADDR_W-1:0]] <= wdata;
            wptr <= wptr + 1'b1;
        end
    end

    // Read port (registered output -- one cycle of read latency, standard
    // for a synchronous FIFO)
    always_ff @(posedge clk or negedge rst_n) begin
        if (!rst_n) begin
            rptr  <= '0;
            rdata <= '0;
        end else if (rd_en_eff) begin
            rdata <= mem[rptr[ADDR_W-1:0]];
            rptr  <= rptr + 1'b1;
        end
    end

    // Full/empty from pointer comparison:
    //   empty : pointers fully match (including the wrap bit)
    //   full  : lower address bits match but the wrap bit differs
    //           (write pointer has lapped the read pointer exactly once)
    assign empty = (wptr == rptr);
    assign full  = (wptr[ADDR_W]     != rptr[ADDR_W]) &&
                   (wptr[ADDR_W-1:0] == rptr[ADDR_W-1:0]);

endmodule

tb_sync_fifo.sv
// =============================================================================
// tb_sync_fifo.sv
// Self-checking testbench for sync_fifo.
// Uses an independent SystemVerilog queue as a golden reference model.
// =============================================================================
`timescale 1ns/1ps

module tb_sync_fifo;

    localparam int DATA_WIDTH = 8;
    localparam int DEPTH      = 8;

    logic                  clk;
    logic                  rst_n;
    logic                  wr_en, rd_en;
    logic [DATA_WIDTH-1:0] wdata, rdata;
    logic                  full, empty;

    int errors = 0;
    int checks = 0;

    sync_fifo #(
        .DATA_WIDTH(DATA_WIDTH),
        .DEPTH(DEPTH)
    ) dut (
        .clk    (clk),
        .rst_n  (rst_n),
        .wr_en  (wr_en),
        .wdata  (wdata),
        .rd_en  (rd_en),
        .rdata  (rdata),
        .full   (full),
        .empty  (empty)
    );

    // 100MHz clock
    initial clk = 0;
    always #5 clk = ~clk;

    // waveform dump
    initial begin
        $dumpfile("sim/fifo_wave.vcd");
        $dumpvars(0, tb_sync_fifo);
    end

    // -------------------------------------------------------------------
    // Golden reference model: a simple SW queue that should always mirror
    // exactly what a correct FIFO contains.
    // -------------------------------------------------------------------
    logic [DATA_WIDTH-1:0] ref_q[$];

    task automatic do_reset();
        rst_n = 0; wr_en = 0; rd_en = 0; wdata = '0;
        repeat (3) @(posedge clk);
        rst_n = 1;
        @(posedge clk);
        ref_q.delete();
    endtask

    // Drives wr_en/rd_en for exactly one clock, checks full/empty/rdata
    // against the reference model, then updates the reference model.
    // This single task is reused for normal writes, normal reads, AND
    // simultaneous read+write -- the same predicted-then-checked pattern
    // covers all three, including the full/empty edge cases.
    task automatic step(input logic w_en, input logic [DATA_WIDTH-1:0] w_data, input logic r_en);
        logic pre_full, pre_empty, do_w, do_r;
        logic [DATA_WIDTH-1:0] expected_rdata;
        int post_size;
        logic exp_full_post, exp_empty_post;

        @(negedge clk);
        wr_en = w_en;
        wdata = w_data;
        rd_en = r_en;

        // Decide whether the write/read actually happens using the
        // reference model's state *before* this edge -- this mirrors
        // wr_en_eff/rd_en_eff in the DUT, which are combinationally
        // derived from the pointers as registered before this edge.
        pre_full  = (ref_q.size() == DEPTH);
        pre_empty = (ref_q.size() == 0);
        do_w = w_en && (!pre_full || r_en);
        do_r = r_en && !pre_empty;
        if (do_r) expected_rdata = ref_q[0];

        // full/empty, however, are sampled from the DUT *after* the edge,
        // once wptr/rptr have already advanced for this cycle. So the
        // correct prediction to compare against is the POST-edge
        // occupancy, not the pre-edge one.
        post_size = ref_q.size() - (do_r ? 1 : 0) + (do_w ? 1 : 0);
        exp_full_post  = (post_size == DEPTH);
        exp_empty_post = (post_size == 0);

        @(posedge clk);
        #1; // let combinational full/empty and the rdata flop settle

        checks++;
        if (full !== exp_full_post) begin
            errors++;
            $error("[%0t] full mismatch: dut=%0b expected=%0b (post-edge size=%0d)", $time, full, exp_full_post, post_size);
        end
        if (empty !== exp_empty_post) begin
            errors++;
            $error("[%0t] empty mismatch: dut=%0b expected=%0b (post-edge size=%0d)", $time, empty, exp_empty_post, post_size);
        end
        if (do_r) begin
            checks++;
            if (rdata !== expected_rdata) begin
                errors++;
                $error("[%0t] rdata mismatch: dut=%0h expected=%0h", $time, rdata, expected_rdata);
            end
        end

        // update reference model to match (order doesn't affect the
        // result since read pops the front and write pushes the back,
        // but pop-then-push mirrors "old data out, new data in")
        if (do_r) ref_q.pop_front();
        if (do_w) ref_q.push_back(w_data);

        wr_en = 0;
        rd_en = 0;
    endtask

    task automatic check(input bit cond, input string msg);
        checks++;
        if (!cond) begin
            errors++;
            $error("[%0t] %s", $time, msg);
        end
    endtask

    // -------------------------------------------------------------------
    // Test sequence
    // -------------------------------------------------------------------
    initial begin
        logic [DATA_WIDTH-1:0] tmp;

        $display("=========================================================");
        $display(" sync_fifo testbench  (DATA_WIDTH=%0d DEPTH=%0d)", DATA_WIDTH, DEPTH);
        $display("=========================================================");

        // --- 1. Reset behavior -----------------------------------------
        $display("[TEST] Reset");
        do_reset();
        check(empty === 1'b1, "after reset: empty should be 1");
        check(full  === 1'b0, "after reset: full should be 0");

        // --- 2. Normal writes + FIFO ordering + normal reads -----------
        // (ordering is verified implicitly: step() predicts each read's
        //  expected value from the reference queue's *front*, so any
        //  reordering bug would show up as an rdata mismatch)
        $display("[TEST] Normal writes, ordering, normal reads");
        for (int i = 0; i < 4; i++) step(1, 8'hA0 + i, 0); // write A0,A1,A2,A3
        for (int i = 0; i < 4; i++) step(0, 8'h00, 1);     // read them back in order
        check(empty === 1'b1, "queue should be empty after draining what we wrote");

        // --- 3. Full condition ------------------------------------------
        $display("[TEST] Full condition");
        do_reset();
        for (int i = 0; i < DEPTH; i++) step(1, 8'hC0 + i, 0);
        check(full === 1'b1, "FIFO should report full after DEPTH writes");
        // Deliberately attempt an overflow write: FIFO must ignore it,
        // not corrupt state. step() already predicts do_w=0 here and
        // will flag an error if the DUT accepted it anyway.
        step(1, 8'hFF, 0);
        check(full === 1'b1, "FIFO should still be full after a rejected overflow write");

        // --- 4. Empty condition ------------------------------------------
        $display("[TEST] Empty condition");
        for (int i = 0; i < DEPTH; i++) step(0, 8'h00, 1); // drain everything
        check(empty === 1'b1, "FIFO should report empty after draining all DEPTH entries");
        // Deliberately attempt an underflow read: must be safely ignored.
        step(0, 8'h00, 1);
        check(empty === 1'b1, "FIFO should still be empty after a rejected underflow read");

        // --- 5. Simultaneous read/write, partially filled ---------------
        $display("[TEST] Simultaneous read/write (partial fill)");
        do_reset();
        step(1, 8'h11, 0);
        step(1, 8'h22, 0);
        step(1, 8'h33, 1); // write 0x33 while reading out 0x11, same cycle

        // --- 6. Simultaneous read/write while FULL -----------------------
        $display("[TEST] Simultaneous read/write while full");
        do_reset();
        for (int i = 0; i < DEPTH; i++) step(1, 8'hD0 + i, 0);
        check(full === 1'b1, "should be full before the full+simultaneous test");
        step(1, 8'hEE, 1); // full: read+write together must be accepted (net occupancy unchanged)
        check(full === 1'b1, "should still be full: one out, one in, net count unchanged");

        // --- 7. Simultaneous read/write while EMPTY -----------------------
        $display("[TEST] Simultaneous read/write while empty");
        do_reset();
        step(1, 8'h55, 1); // empty: write must succeed, read must be dropped (nothing to read)
        check(empty === 1'b0, "one entry should now be present");

        // --- 8. Boundary: wrap the pointers all the way around twice ----
        $display("[TEST] Pointer wraparound (boundary case)");
        do_reset();
        for (int cycle = 0; cycle < 3; cycle++) begin
            for (int i = 0; i < DEPTH; i++) step(1, i[DATA_WIDTH-1:0] + cycle[DATA_WIDTH-1:0]*8'h10, 0);
            check(full === 1'b1, "should be full at end of wraparound fill");
            for (int i = 0; i < DEPTH; i++) step(0, 8'h00, 1);
            check(empty === 1'b1, "should be empty at end of wraparound drain");
        end

        // --- 9. Randomized stress test against the reference model ------
        $display("[TEST] Randomized stress (500 cycles)");
        do_reset();
        for (int i = 0; i < 500; i++) begin
            bit w, r;
            logic [DATA_WIDTH-1:0] d;
            w = $urandom_range(0, 1);
            r = $urandom_range(0, 1);
            d = $urandom_range(0, 255);
            step(w, d, r);
        end

        // --- Summary ------------------------------------------------------
        $display("=========================================================");
        if (errors == 0)
            $display(" RESULT: PASS  (%0d checks, 0 errors)", checks);
        else
            $display(" RESULT: FAIL  (%0d checks, %0d errors)", checks, errors);
        $display("=========================================================");

        $finish;
    end

    // Safety timeout in case something hangs
    initial begin
        #200000;
        $display("ERROR: testbench timeout - simulation did not finish");
        $finish;
    end

endmodule

sim/fifo_wave.vcd
$date
	Wed Aug 12 22:44:38 2026
$end
$version
	Icarus Verilog
$end
$timescale
	1ps
$end
$scope module tb_sync_fifo $end
$var wire 8 ! rdata [7:0] $end
$var wire 1 " full $end
$var wire 1 # empty $end
$var parameter 32 $ DATA_WIDTH $end
$var parameter 32 % DEPTH $end
$var reg 1 & clk $end
$var reg 1 ' rd_en $end
$var reg 1 ( rst_n $end
$var reg 8 ) wdata [7:0] $end
$var reg 1 * wr_en $end
$var integer 32 + checks [31:0] $end
$var integer 32 , errors [31:0] $end
$scope module dut $end
$var wire 1 & clk $end
$var wire 1 " full $end
$var wire 1 ' rd_en $end
$var wire 1 - rd_en_eff $end
$var wire 1 ( rst_n $end
$var wire 8 . wdata [7:0] $end
$var wire 1 * wr_en $end
$var wire 1 / wr_en_eff $end
$var wire 1 # empty $end
$var parameter 32 0 ADDR_W $end
$var parameter 32 1 DATA_WIDTH $end
$var parameter 32 2 DEPTH $end
$var reg 8 3 rdata [7:0] $end
$var reg 4 4 rptr [3:0] $end
$var reg 4 5 wptr [3:0] $end
$upscope $end
$scope begin $unm_blk_13 $end
$scope begin $ivl_for_loop0 $end
$var integer 32 6 i [31:0] $end
$upscope $end
$scope begin $ivl_for_loop1 $end
$var integer 32 7 i [31:0] $end
$upscope $end
$scope begin $ivl_for_loop2 $end
$var integer 32 8 i [31:0] $end
$upscope $end
$scope begin $ivl_for_loop3 $end
$var integer 32 9 i [31:0] $end
$upscope $end
$scope begin $ivl_for_loop4 $end
$var integer 32 : i [31:0] $end
$upscope $end
$scope begin $ivl_for_loop5 $end
$var integer 32 ; cycle [31:0] $end
$scope begin $ivl_for_loop6 $end
$var integer 32 < i [31:0] $end
$upscope $end
$scope begin $ivl_for_loop7 $end
$var integer 32 = i [31:0] $end
$upscope $end
$upscope $end
$scope begin $ivl_for_loop8 $end
$var integer 32 > i [31:0] $end
$scope begin $unm_blk_15 $end
$var reg 8 ? d [7:0] $end
$var reg 1 @ r $end
$var reg 1 A w $end
$upscope $end
$upscope $end
$upscope $end
$scope task check $end
$upscope $end
$scope task do_reset $end
$upscope $end
$scope task step $end
$upscope $end
$upscope $end
$enddefinitions $end
$comment Show the parameter values. $end
$dumpall
b1000 2
b1000 1
b11 0
b1000 %
b1000 $
$end
#0
$dumpvars
0A
0@
bx ?
b0 >
b0 =
b0 <
b0 ;
b0 :
b0 9
b0 8
b0 7
b0 6
b0 5
b0 4
b0 3
0/
b0 .
0-
b0 ,
b0 +
0*
b0 )
0(
0'
0&
1#
0"
b0 !
$end
#5000
1&
#10000
0&
#15000
1&
#20000
0&
#25000
1(
1&
#30000
0&
#35000
b10 +
1&
#40000
1/
b10100000 )
b10100000 .
1*
0&
#45000
0#
b1 5
1&
#46000
0/
b1 6
0*
b11 +
#50000
1/
b10100001 )
b10100001 .
1*
0&
#55000
b10 5
1&
#56000
0/
b10 6
0*
b100 +
#60000
1/
b10100010 )
b10100010 .
1*
0&
#65000
b11 5
1&
#66000
0/
b11 6
0*
b101 +
#70000
1/
b10100011 )
b10100011 .
1*
0&
#75000
b100 5
1&
#76000
0/
b100 6
0*
b110 +
#80000
1-
1'
b0 )
b0 .
0&
#85000
b1 4
b10100000 !
b10100000 3
1&
#86000
0-
b1 7
0'
b1000 +
#90000
1-
1'
0&
#95000
b10 4
b10100001 !
b10100001 3
1&
#96000
0-
b10 7
0'
b1010 +
#100000
1-
1'
0&
#105000
b11 4
b10100010 !
b10100010 3
1&
#106000
0-
b11 7
0'
b1100 +
#110000
1-
1'
0&
#115000
0-
1#
b100 4
b10100011 !
b10100011 3
1&
#116000
b0 !
b0 3
b0 4
1#
b0 5
0(
b100 7
0'
b1111 +
#120000
0&
#125000
1&
#130000
0&
#135000
1&
#140000
0&
#145000
1(
1&
#150000
0&
#155000
1&
#160000
1/
b11000000 )
b11000000 .
1*
0&
#165000
0#
b1 5
1&
#166000
0/
b1 8
0*
b10000 +
#170000
1/
b11000001 )
b11000001 .
1*
0&
#175000
b10 5
1&
#176000
0/
b10 8
0*
b10001 +
#180000
1/
b11000010 )
b11000010 .
1*
0&
#185000
b11 5
1&
#186000
0/
b11 8
0*
b10010 +
#190000
1/
b11000011 )
b11000011 .
1*
0&
#195000
b100 5
1&
#196000
0/
b100 8
0*
b10011 +
#200000
1/
b11000100 )
b11000100 .
1*
0&
#205000
b101 5
1&
#206000
0/
b101 8
0*
b10100 +
#210000
1/
b11000101 )
b11000101 .
1*
0&
#215000
b110 5
1&
#216000
0/
b110 8
0*
b10101 +
#220000
1/
b11000110 )
b11000110 .
1*
0&
#225000
b111 5
1&
#226000
0/
b111 8
0*
b10110 +
#230000
1/
b11000111 )
b11000111 .
1*
0&
#235000
0/
1"
b1000 5
1&
#236000
b1000 8
0*
b11000 +
#240000
b11111111 )
b11111111 .
1*
0&
#245000
1&
#246000
0*
b11010 +
#250000
1-
1'
b0 )
b0 .
0&
#255000
0"
b1 4
b11000000 !
b11000000 3
1&
#256000
0-
b1 9
0'
b11100 +
#260000
1-
1'
0&
#265000
b10 4
b11000001 !
b11000001 3
1&
#266000
0-
b10 9
0'
b11110 +
#270000
1-
1'
0&
#275000
b11 4
b11000010 !
b11000010 3
1&
#276000
0-
b11 9
0'
b100000 +
#280000
1-
1'
0&
#285000
b100 4
b11000011 !
b11000011 3
1&
#286000
0-
b100 9
0'
b100010 +
#290000
1-
1'
0&
#295000
b101 4
b11000100 !
b11000100 3
1&
#296000
0-
b101 9
0'
b100100 +
#300000
1-
1'
0&
#305000
b110 4
b11000101 !
b11000101 3
1&
#306000
0-
b110 9
0'
b100110 +
#310000
1-
1'
0&
#315000
b111 4
b11000110 !
b11000110 3
1&
#316000
0-
b111 9
0'
b101000 +
#320000
1-
1'
0&
#325000
0"
0-
1#
b1000 4
b11000111 !
b11000111 3
1&
#326000
b1000 9
0'
b101011 +
#330000
1'
0&
#335000
1&
#336000
b0 5
b0 !
b0 3
1#
b0 4
0(
0'
b101101 +
#340000
0&
#345000
1&
#350000
0&
#355000
1&
#360000
0&
#365000
1(
1&
#370000
0&
#375000
1&
#380000
1/
b10001 )
b10001 .
1*
0&
#385000
0#
b1 5
1&
#386000
0/
0*
b101110 +
#390000
1/
b100010 )
b100010 .
1*
0&
#395000
b10 5
1&
#396000
0/
0*
b101111 +
#400000
1-
1/
1'
b110011 )
b110011 .
1*
0&
#405000
b1 4
b10001 !
b10001 3
b11 5
1&
#406000
1#
b0 5
b0 !
b0 3
b0 4
0-
0/
b0 )
b0 .
0(
0'
0*
b110001 +
#410000
0&
#415000
1&
#420000
0&
#425000
1&
#430000
0&
#435000
1(
1&
#440000
0&
#445000
1&
#450000
1/
b11010000 )
b11010000 .
1*
0&
#455000
0#
b1 5
1&
#456000
0/
b1 :
0*
b110010 +
#460000
1/
b11010001 )
b11010001 .
1*
0&
#465000
b10 5
1&
#466000
0/
b10 :
0*
b110011 +
#470000
1/
b11010010 )
b11010010 .
1*
0&
#475000
b11 5
1&
#476000
0/
b11 :
0*
b110100 +
#480000
1/
b11010011 )
b11010011 .
1*
0&
#485000
b100 5
1&
#486000
0/
b100 :
0*
b110101 +
#490000
1/
b11010100 )
b11010100 .
1*
0&
#495000
b101 5
1&
#496000
0/
b101 :
0*
b110110 +
#500000
1/
b11010101 )
b11010101 .
1*
0&
#505000
b110 5
1&
#506000
0/
b110 :
0*
b110111 +
#510000
1/
b11010110 )
b11010110 .
1*
0&
#515000
b111 5
1&
#516000
0/
b111 :
0*
b111000 +
#520000
1/
b11010111 )
b11010111 .
1*
0&
#525000
0/
1"
b1000 5
1&
#526000
b1000 :
0*
b111010 +
#530000
1/
1-
1'
b11101110 )
b11101110 .
1*
0&
#535000
b1 4
b11010000 !
b11010000 3
b1001 5
1&
#536000
0"
1#
b0 5
b0 !
b0 3
b0 4
0-
0/
b0 )
b0 .
0(
0'
0*
b111101 +
#540000
0&
#545000
1&
#550000
0&
#555000
1&
#560000
0&
#565000
1(
1&
#570000
0&
#575000
1&
#580000
1/
1'
b1010101 )
b1010101 .
1*
0&
#585000
1-
0#
b1 5
1&
#586000
1#
b0 5
0-
0/
b0 )
b0 .
0(
0'
0*
b111111 +
#590000
0&
#595000
1&
#600000
0&
#605000
1&
#610000
0&
#615000
1(
1&
#620000
0&
#625000
1&
#630000
1/
1*
0&
#635000
0#
b1 5
1&
#636000
0/
b1 <
0*
b1000000 +
#640000
1/
b1 )
b1 .
1*
0&
#645000
b10 5
1&
#646000
0/
b10 <
0*
b1000001 +
#650000
1/
b10 )
b10 .
1*
0&
#655000
b11 5
1&
#656000
0/
b11 <
0*
b1000010 +
#660000
1/
b11 )
b11 .
1*
0&
#665000
b100 5
1&
#666000
0/
b100 <
0*
b1000011 +
#670000
1/
b100 )
b100 .
1*
0&
#675000
b101 5
1&
#676000
0/
b101 <
0*
b1000100 +
#680000
1/
b101 )
b101 .
1*
0&
#685000
b110 5
1&
#686000
0/
b110 <
0*
b1000101 +
#690000
1/
b110 )
b110 .
1*
0&
#695000
b111 5
1&
#696000
0/
b111 <
0*
b1000110 +
#700000
1/
b111 )
b111 .
1*
0&
#705000
0/
1"
b1000 5
1&
#706000
b1000 <
0*
b1001000 +
#710000
1-
1'
b0 )
b0 .
0&
#715000
0"
b1 4
1&
#716000
0-
b1 =
0'
b1001010 +
#720000
1-
1'
0&
#725000
b10 4
b1 !
b1 3
1&
#726000
0-
b10 =
0'
b1001100 +
#730000
1-
1'
0&
#735000
b11 4
b10 !
b10 3
1&
#736000
0-
b11 =
0'
b1001110 +
#740000
1-
1'
0&
#745000
b100 4
b11 !
b11 3
1&
#746000
0-
b100 =
0'
b1010000 +
#750000
1-
1'
0&
#755000
b101 4
b100 !
b100 3
1&
#756000
0-
b101 =
0'
b1010010 +
#760000
1-
1'
0&
#765000
b110 4
b101 !
b101 3
1&
#766000
0-
b110 =
0'
b1010100 +
#770000
1-
1'
0&
#775000
b111 4
b110 !
b110 3
1&
#776000
0-
b111 =
0'
b1010110 +
#780000
1-
1'
0&
#785000
0"
0-
1#
b1000 4
b111 !
b111 3
1&
#786000
b0 <
b1 ;
b1000 =
0'
b1011001 +
#790000
1/
b10000 )
b10000 .
1*
0&
#795000
0#
b1001 5
1&
#796000
0/
b1 <
0*
b1011010 +
#800000
1/
b10001 )
b10001 .
1*
0&
#805000
b1010 5
1&
#806000
0/
b10 <
0*
b1011011 +
#810000
1/
b10010 )
b10010 .
1*
0&
#815000
b1011 5
1&
#816000
0/
b11 <
0*
b1011100 +
#820000
1/
b10011 )
b10011 .
1*
0&
#825000
b1100 5
1&
#826000
0/
b100 <
0*
b1011101 +
#830000
1/
b10100 )
b10100 .
1*
0&
#835000
b1101 5
1&
#836000
0/
b101 <
0*
b1011110 +
#840000
1/
b10101 )
b10101 .
1*
0&
#845000
b1110 5
1&
#846000
0/
b110 <
0*
b1011111 +
#850000
1/
b10110 )
b10110 .
1*
0&
#855000
b1111 5
1&
#856000
0/
b111 <
0*
b1100000 +
#860000
1/
b10111 )
b10111 .
1*
0&
#865000
0/
1"
b0 5
1&
#866000
b0 =
b1000 <
0*
b1100010 +
#870000
1-
1'
b0 )
b0 .
0&
#875000
0"
b1001 4
b10000 !
b10000 3
1&
#876000
0-
b1 =
0'
b1100100 +
#880000
1-
1'
0&
#885000
b1010 4
b10001 !
b10001 3
1&
#886000
0-
b10 =
0'
b1100110 +
#890000
1-
1'
0&
#895000
b1011 4
b10010 !
b10010 3
1&
#896000
0-
b11 =
0'
b1101000 +
#900000
1-
1'
0&
#905000
b1100 4
b10011 !
b10011 3
1&
#906000
0-
b100 =
0'
b1101010 +
#910000
1-
1'
0&
#915000
b1101 4
b10100 !
b10100 3
1&
#916000
0-
b101 =
0'
b1101100 +
#920000
1-
1'
0&
#925000
b1110 4
b10101 !
b10101 3
1&
#926000
0-
b110 =
0'
b1101110 +
#930000
1-
1'
0&
#935000
b1111 4
b10110 !
b10110 3
1&
#936000
0-
b111 =
0'
b1110000 +
#940000
1-
1'
0&
#945000
0"
0-
1#
b0 4
b10111 !
b10111 3
1&
#946000
b0 <
b10 ;
b1000 =
0'
b1110011 +
#950000
1/
b100000 )
b100000 .
1*
0&
#955000
0#
b1 5
1&
#956000
0/
b1 <
0*
b1110100 +
#960000
1/
b100001 )
b100001 .
1*
0&
#965000
b10 5
1&
#966000
0/
b10 <
0*
b1110101 +
#970000
1/
b100010 )
b100010 .
1*
0&
#975000
b11 5
1&
#976000
0/
b11 <
0*
b1110110 +
#980000
1/
b100011 )
b100011 .
1*
0&
#985000
b100 5
1&
#986000
0/
b100 <
0*
b1110111 +
#990000
1/
b100100 )
b100100 .
1*
0&
#995000
b101 5
1&
#996000
0/
b101 <
0*
b1111000 +
#1000000
1/
b100101 )
b100101 .
1*
0&
#1005000
b110 5
1&
#1006000
0/
b110 <
0*
b1111001 +
#1010000
1/
b100110 )
b100110 .
1*
0&
#1015000
b111 5
1&
#1016000
0/
b111 <
0*
b1111010 +
#1020000
1/
b100111 )
b100111 .
1*
0&
#1025000
0/
1"
b1000 5
1&
#1026000
b0 =
b1000 <
0*
b1111100 +
#1030000
1-
1'
b0 )
b0 .
0&
#1035000
0"
b1 4
b100000 !
b100000 3
1&
#1036000
0-
b1 =
0'
b1111110 +
#1040000
1-
1'
0&
#1045000
b10 4
b100001 !
b100001 3
1&
#1046000
0-
b10 =
0'
b10000000 +
#1050000
1-
1'
0&
#1055000
b11 4
b100010 !
b100010 3
1&
#1056000
0-
b11 =
0'
b10000010 +
#1060000
1-
1'
0&
#1065000
b100 4
b100011 !
b100011 3
1&
#1066000
0-
b100 =
0'
b10000100 +
#1070000
1-
1'
0&
#1075000
b101 4
b100100 !
b100100 3
1&
#1076000
0-
b101 =
0'
b10000110 +
#1080000
1-
1'
0&
#1085000
b110 4
b100101 !
b100101 3
1&
#1086000
0-
b110 =
0'
b10001000 +
#1090000
1-
1'
0&
#1095000
b111 4
b100110 !
b100110 3
1&
#1096000
0-
b111 =
0'
b10001010 +
#1100000
1-
1'
0&
#1105000
0"
0-
1#
b1000 4
b100111 !
b100111 3
1&
#1106000
b0 !
b0 3
b0 4
1#
b0 5
0(
b11 ;
b1000 =
0'
b10001101 +
#1110000
0&
#1115000
1&
#1120000
0&
#1125000
1&
#1130000
0&
#1135000
1(
1&
#1140000
0&
#1145000
b100 ?
1A
1&
#1150000
1/
b100 )
b100 .
1*
0&
#1155000
0#
b1 5
1&
#1156000
0/
b11000110 ?
1@
0A
b1 >
0*
b10001110 +
#1160000
1-
1'
b11000110 )
b11000110 .
0&
#1165000
0-
1#
b1 4
b100 !
b100 3
1&
#1166000
b10000000 ?
0@
b10 >
0'
b10010000 +
#1170000
b10000000 )
b10000000 .
0&
#1175000
1&
#1176000
b10011110 ?
1@
1A
b11 >
b10010001 +
#1180000
1/
1'
b10011110 )
b10011110 .
1*
0&
#1185000
1-
0#
b10 5
1&
#1186000
0-
0/
b11111100 ?
b100 >
0'
0*
b10010010 +
#1190000
1-
1/
1'
b11111100 )
b11111100 .
1*
0&
#1195000
b11 5
0#
b10 4
b10011110 !
b10011110 3
1&
#1196000
0-
0/
b1010101 ?
0@
0A
b101 >
0'
0*
b10010100 +
#1200000
b1010101 )
b1010101 .
0&
#1205000
1&
#1206000
b1001 ?
1A
b110 >
b10010101 +
#1210000
1/
b1001 )
b1001 .
1*
0&
#1215000
b100 5
1&
#1216000
0/
b1100111 ?
1@
b111 >
0*
b10010110 +
#1220000
1-
1/
1'
b1100111 )
b1100111 .
1*
0&
#1225000
b11 4
b11111100 !
b11111100 3
b101 5
1&
#1226000
0-
0/
b10101110 ?
0@
0A
b1000 >
0'
0*
b10011000 +
#1230000
b10101110 )
b10101110 .
0&
#1235000
1&
#1236000
b110010 ?
b1001 >
b10011001 +
#1240000
b110010 )
b110010 .
0&
#1245000
1&
#1246000
b1000000 ?
1@
b1010 >
b10011010 +
#1250000
1-
1'
b1000000 )
b1000000 .
0&
#1255000
b100 4
b1001 !
b1001 3
1&
#1256000
0-
b1001110 ?
1A
b1011 >
0'
b10011100 +
#1260000
1-
1/
1'
b1001110 )
b1001110 .
1*
0&
#1265000
b101 4
b1100111 !
b1100111 3
b110 5
1&
#1266000
0-
0/
b110 ?
0@
0A
b1100 >
0'
0*
b10011110 +
#1270000
b110 )
b110 .
0&
#1275000
1&
#1276000
b1101010 ?
1@
b1101 >
b10011111 +
#1280000
1-
1'
b1101010 )
b1101010 .
0&
#1285000
0-
1#
b110 4
b1001110 !
b1001110 3
1&
#1286000
b10001110 ?
0@
b1110 >
0'
b10100001 +
#1290000
b10001110 )
b10001110 .
0&
#1295000
1&
#1296000
b10000101 ?
1@
b1111 >
b10100010 +
#1300000
1'
b10000101 )
b10000101 .
0&
#1305000
1&
#1306000
b11111001 ?
0@
b10000 >
0'
b10100011 +
#1310000
b11111001 )
b11111001 .
0&
#1315000
1&
#1316000
b1101100 ?
1@
1A
b10001 >
b10100100 +
#1320000
1/
1'
b1101100 )
b1101100 .
1*
0&
#1325000
1-
0#
b111 5
1&
#1326000
0-
0/
b11110101 ?
0@
b10010 >
0'
0*
b10100101 +
#1330000
1/
b11110101 )
b11110101 .
1*
0&
#1335000
b1000 5
1&
#1336000
0/
b11010111 ?
1@
b10011 >
0*
b10100110 +
#1340000
1-
1/
1'
b11010111 )
b11010111 .
1*
0&
#1345000
b111 4
b1101100 !
b1101100 3
b1001 5
1&
#1346000
0-
0/
b101 ?
0A
b10100 >
0'
0*
b10101000 +
#1350000
1-
1'
b101 )
b101 .
0&
#1355000
b1000 4
b11110101 !
b11110101 3
1&
#1356000
0-
b10100111 ?
b10101 >
0'
b10101010 +
#1360000
1-
1'
b10100111 )
b10100111 .
0&
#1365000
0-
1#
b1001 4
b11010111 !
b11010111 3
1&
#1366000
b111111 ?
b10110 >
0'
b10101100 +
#1370000
1'
b111111 )
b111111 .
0&
#1375000
1&
#1376000
b11101100 ?
1A
b10111 >
0'
b10101101 +
#1380000
1/
1'
b11101100 )
b11101100 .
1*
0&
#1385000
1-
0#
b1010 5
1&
#1386000
0-
0/
b11001111 ?
b11000 >
0'
0*
b10101110 +
#1390000
1-
1/
1'
b11001111 )
b11001111 .
1*
0&
#1395000
b1011 5
0#
b1010 4
b11101100 !
b11101100 3
1&
#1396000
0-
0/
b1011011 ?
b11001 >
0'
0*
b10110000 +
#1400000
1-
1/
1'
b1011011 )
b1011011 .
1*
0&
#1405000
b1011 4
b11001111 !
b11001111 3
b1100 5
1&
#1406000
0-
0/
b101101 ?
0@
0A
b11010 >
0'
0*
b10110010 +
#1410000
b101101 )
b101101 .
0&
#1415000
1&
#1416000
b1101000 ?
1A
b11011 >
b10110011 +
#1420000
1/
b1101000 )
b1101000 .
1*
0&
#1425000
b1101 5
1&
#1426000
0/
b11001011 ?
0A
b11100 >
0*
b10110100 +
#1430000
b11001011 )
b11001011 .
0&
#1435000
1&
#1436000
b11100100 ?
1A
b11101 >
b10110101 +
#1440000
1/
b11100100 )
b11100100 .
1*
0&
#1445000
b1110 5
1&
#1446000
0/
b10001001 ?
1@
0A
b11110 >
0*
b10110110 +
#1450000
1-
1'
b10001001 )
b10001001 .
0&
#1455000
b1100 4
b1011011 !
b1011011 3
1&
#1456000
0-
b10011100 ?
b11111 >
0'
b10111000 +
#1460000
1-
1'
b10011100 )
b10011100 .
0&
#1465000
b1101 4
b1101000 !
b1101000 3
1&
#1466000
0-
b11000010 ?
0@
1A
b100000 >
0'
b10111010 +
#1470000
1/
b11000010 )
b11000010 .
1*
0&
#1475000
b1111 5
1&
#1476000
0/
b10100100 ?
1@
0A
b100001 >
0*
b10111011 +
#1480000
1-
1'
b10100100 )
b10100100 .
0&
#1485000
b1110 4
b11100100 !
b11100100 3
1&
#1486000
0-
b10101100 ?
b100010 >
0'
b10111101 +
#1490000
1-
1'
b10101100 )
b10101100 .
0&
#1495000
0-
1#
b1111 4
b11000010 !
b11000010 3
1&
#1496000
b1001110 ?
0@
b100011 >
0'
b10111111 +
#1500000
b1001110 )
b1001110 .
0&
#1505000
1&
#1506000
b10111001 ?
1A
b100100 >
b11000000 +
#1510000
1/
b10111001 )
b10111001 .
1*
0&
